spatial_cluster_helper/__init__.py
spatial_cluster_helper/spatial_cluster_helper.py
spatial_cluster_helper-0.1.3.dist-info/METADATA
spatial_cluster_helper-0.1.3.dist-info/WHEEL
spatial_cluster_helper-0.1.3.dist-info/top_level.txt
spatial_cluster_helper-0.1.3.dist-info/RECORD
