Metadata-Version: 2.1
Name: spatial_cluster_helper
Version: 0.1.3
Summary: A package for spatial clustering and analysis
Home-page: https://github.com/lanselin/notebooks_for_spatial_clustering
Author: Luc Anselin, Pedro Amaral
Author-email: Luc Anselin <lanselin@gmail.com>, Pedro Amaral <pedrovma.ufmg@gmail.com>
License: MIT
Project-URL: Homepage, https://github.com/lanselin/notebooks_for_spatial_clustering
Project-URL: Repository, https://github.com/lanselin/notebooks_for_spatial_clustering
Requires-Python: >=3.12
Requires-Dist: numpy
Requires-Dist: pandas
Requires-Dist: geopandas
Requires-Dist: scikit-learn
Requires-Dist: scipy
Requires-Dist: matplotlib
Requires-Dist: libpysal
